jupyterlab_autorun_cells/__init__.py
jupyterlab_autorun_cells/_version.py
jupyterlab_autorun_cells/labextension/build_log.json
jupyterlab_autorun_cells/labextension/package.json
jupyterlab_autorun_cells/labextension/static/lib_index_js.0543661bfae35f8d7291.js
jupyterlab_autorun_cells/labextension/static/lib_index_js.0543661bfae35f8d7291.js.map
jupyterlab_autorun_cells/labextension/static/remoteEntry.71c62d5e31adfb055ab4.js
jupyterlab_autorun_cells/labextension/static/remoteEntry.71c62d5e31adfb055ab4.js.map
jupyterlab_autorun_cells/labextension/static/style.js
jupyterlab_autorun_cells/labextension/static/style_index_js.21b1487c08fbd17c05cc.js
jupyterlab_autorun_cells/labextension/static/style_index_js.21b1487c08fbd17c05cc.js.map
jupyterlab_autorun_cells/labextension/static/vendors-node_modules_css-loader_dist_runtime_api_js-node_modules_css-loader_dist_runtime_cssW-926fd9.21a39f2d029f36f163ee.js
jupyterlab_autorun_cells/labextension/static/vendors-node_modules_css-loader_dist_runtime_api_js-node_modules_css-loader_dist_runtime_cssW-926fd9.21a39f2d029f36f163ee.js.map
jupyterlab_autorun_cells-1.0.0.data/data/share/jupyter/labextensions/@epi2melabs/jupyterlab-autorun-cells/build_log.json
jupyterlab_autorun_cells-1.0.0.data/data/share/jupyter/labextensions/@epi2melabs/jupyterlab-autorun-cells/install.json
jupyterlab_autorun_cells-1.0.0.data/data/share/jupyter/labextensions/@epi2melabs/jupyterlab-autorun-cells/package.json
jupyterlab_autorun_cells-1.0.0.data/data/share/jupyter/labextensions/@epi2melabs/jupyterlab-autorun-cells/static/lib_index_js.0543661bfae35f8d7291.js
jupyterlab_autorun_cells-1.0.0.data/data/share/jupyter/labextensions/@epi2melabs/jupyterlab-autorun-cells/static/lib_index_js.0543661bfae35f8d7291.js.map
jupyterlab_autorun_cells-1.0.0.data/data/share/jupyter/labextensions/@epi2melabs/jupyterlab-autorun-cells/static/remoteEntry.71c62d5e31adfb055ab4.js
jupyterlab_autorun_cells-1.0.0.dist-info/LICENSE
jupyterlab_autorun_cells-1.0.0.dist-info/METADATA
jupyterlab_autorun_cells-1.0.0.dist-info/WHEEL
jupyterlab_autorun_cells-1.0.0.dist-info/top_level.txt
jupyterlab_autorun_cells-1.0.0.dist-info/RECORD
